datasync/__init__.py
datasync/cli.py
datasync/core.py
datasync_utils-1.1.0.dist-info/METADATA
datasync_utils-1.1.0.dist-info/WHEEL
datasync_utils-1.1.0.dist-info/entry_points.txt
datasync_utils-1.1.0.dist-info/top_level.txt
datasync_utils-1.1.0.dist-info/RECORD
