Metadata-Version: 2.4
Name: datasync-utils
Version: 1.1.0
Summary: Unified DVC + S3 data sync for Python, notebooks, and CLI
Requires-Python: >=3.8
Requires-Dist: dvc[s3]
Requires-Dist: typer
